Qart/Error.py
Qart/Table.py
Qart/__init__.py
Qart/canvas.py
Qart/encode.py
Qart/img.py
Qart/qart.py
Qart/qrcode.py
tests/__init__.py
tests/test_canvas.py
tests/test_encode.py
tests/test_img.py
tests/test_qart.py
tests/test_qrcode.py
Qart-0.0.20.dist-info/LICENSE.txt
Qart-0.0.20.dist-info/METADATA
Qart-0.0.20.dist-info/WHEEL
Qart-0.0.20.dist-info/top_level.txt
Qart-0.0.20.dist-info/RECORD
