Metadata-Version: 2.1
Name: Qart
Version: 0.0.20
Summary: A short description of your package
Home-page: https://github.com/as6325400/Qart
Author: as6325400
Author-email: as6325400@gmail.com
License: MIT
Platform: UNKNOWN
Classifier: Programming Language :: Python :: 3
Classifier: License :: OSI Approved :: MIT License
Classifier: Operating System :: OS Independent
Requires-Python: >=3.6
License-File: LICENSE.txt
Requires-Dist: chardet (>=5.2.0)
Requires-Dist: matplotlib (>=3.8.2)
Requires-Dist: numpy (>=1.26.4)
Requires-Dist: opencv-python (>=4.9.0.80)
Requires-Dist: reedsolo (==1.7.0)
